.editorconfig
.gitattributes
.travis.yml
AUTHORS
CONTRIBUTING.rst
ChangeLog
LICENSE
README.rst
requirements.txt
setup.cfg
setup.py
test-requirements.txt
tox.ini
upload.sh
sphinxcontrib/SwaggerAPIContext.py
sphinxcontrib/__init__.py
sphinxcontrib/swagger2.py
sphinxcontrib_sphinx_swagger2_api_doc.egg-info/PKG-INFO
sphinxcontrib_sphinx_swagger2_api_doc.egg-info/SOURCES.txt
sphinxcontrib_sphinx_swagger2_api_doc.egg-info/dependency_links.txt
sphinxcontrib_sphinx_swagger2_api_doc.egg-info/namespace_packages.txt
sphinxcontrib_sphinx_swagger2_api_doc.egg-info/not-zip-safe
sphinxcontrib_sphinx_swagger2_api_doc.egg-info/pbr.json
sphinxcontrib_sphinx_swagger2_api_doc.egg-info/requires.txt
sphinxcontrib_sphinx_swagger2_api_doc.egg-info/top_level.txt
tests/conftest.py
tests/test.jinja2